NandhaAPI/__init__.py
NandhaAPI-0.1.dist-info/LICENSE
NandhaAPI-0.1.dist-info/METADATA
NandhaAPI-0.1.dist-info/WHEEL
NandhaAPI-0.1.dist-info/top_level.txt
NandhaAPI-0.1.dist-info/RECORD
