Metadata-Version: 2.1
Name: NandhaAPI
Version: 0.1
Summary: my python api tool | NandhaAPI
Home-page: https://github.com/nandhaxd/NandhaAPI
Download-URL: https://github.com/nandhaxd/NandhaAPI/blob/main/README.md
Author: Nandhagopal K
Author-email: nandhaxd@gmail.com
License: MIT
Project-URL: Tracker, https://github.com/nandhaxd/NandhaAPI/issues
Project-URL: Community, https://t.me/nandhasupport
Project-URL: Source, https://github.com/nandhaxd/NandhaAPI
Keywords: python,NandhaAPI,NandhaBots,tgbotapi,Tgbots
Classifier: Development Status :: 5 - Production/Stable
Classifier: Intended Audience :: Developers
Classifier: Natural Language :: English
Classifier: Operating System :: OS Independent
Classifier: Programming Language :: Python
Classifier: Programming Language :: Python :: 3
Classifier: Programming Language :: Python :: 3.7
Classifier: Programming Language :: Python :: 3.8
Classifier: Programming Language :: Python :: 3.9
Classifier: Programming Language :: Python :: 3.10
Classifier: Programming Language :: Python :: 3.11
Classifier: Programming Language :: Python :: 3.12
Classifier: Programming Language :: Python :: Implementation
Classifier: Programming Language :: Python :: Implementation :: CPython
Classifier: Programming Language :: Python :: Implementation :: PyPy
Classifier: Topic :: Internet
Classifier: Topic :: Communications
Classifier: Topic :: Communications :: Chat
Classifier: Topic :: Software Development :: Libraries
Classifier: Topic :: Software Development :: Libraries :: Python Modules
Classifier: Topic :: Software Development :: Libraries :: Application Frameworks
Requires-Python: ~=3.7
License-File: LICENSE
Requires-Dist: requests
